comicinfoxml.py
comicinfoxml-0.5.0.dist-info/licenses/LICENSE
comicinfoxml-0.5.0.dist-info/METADATA
comicinfoxml-0.5.0.dist-info/WHEEL
comicinfoxml-0.5.0.dist-info/entry_points.txt
comicinfoxml-0.5.0.dist-info/top_level.txt
comicinfoxml-0.5.0.dist-info/RECORD
