Metadata-Version: 2.4
Name: comicinfoxml
Version: 0.5.0
Summary: A metadata plugin for ComicTagger implementing the ComicInfo.xml from the anansi project
Author-email: Timmy Welch <timmy@narnian.us>
License: MIT
Project-URL: Homepage, https://github.com/comictagger/comicinfoxml
Classifier: License :: OSI Approved :: MIT License
Classifier: Programming Language :: Python :: 3
Classifier: Programming Language :: Python :: 3 :: Only
Classifier: Programming Language :: Python :: Implementation :: CPython
Classifier: Programming Language :: Python :: Implementation :: PyPy
Requires-Python: >=3.8
License-File: LICENSE
Requires-Dist: typing-extensions>=4.3.0; python_version < "3.11"
Dynamic: license-file
